{"id":4069,"updated":"2015-05-17T21:18:19Z","canton":"Aargau","cantonName":"AG","council":"N","faction":"S","factionName":"Sozialdemokratische Fraktion","firstName":"Yvonne","function":"Mitglied","lastName":"Feri","number":2777,"party":"SP","partyName":"Sozialdemokratische Partei der Schweiz","active":true,"additionalActivity":"Co-Präsidentin der Parlamentarischen Gruppe KAIRO+; Co-Präsidentin der Parlamentarischen Frauengruppe","additionalMandate":"Präsidentin SP Wettingen: von März 2001 bis März 2005; Präsidentin SP Bezirk Baden: von März 2008 bis März 2012; Präsidentin der GL SP Frauen Schweiz: seit August 2012; Mitglied der GL SP Schweiz: seit August 2012","birthDate":"1966-03-21T00:00:00Z","birthPlace":{"canton":"AG","city":"Baden"},"code":null,"committeeMemberships":[{"id":0,"updated":"2013-11-25T11:52:39Z","entryDate":"2011-12-15T00:00:00Z","leavingDate":"2013-11-24T00:00:00Z","committee":{"id":3,"updated":"2010-12-26T13:06:13Z","abbreviation":"GPK","code":"KOM_3_","committeeNumber":3,"council":{"id":1,"updated":"2010-12-26T13:07:49Z","abbreviation":"NR","code":"RAT_1_","name":"Nationalrat","type":"N"},"name":"Geschäftsprüfungskommission NR"},"function":null},{"id":1,"updated":"2011-12-21T17:50:44Z","entryDate":"2011-12-15T00:00:00Z","committee":{"id":30,"updated":"2010-12-26T13:06:13Z","abbreviation":"RedK","code":"KOM_30_","committeeNumber":30,"council":{"id":3,"updated":"2010-12-26T13:07:49Z","abbreviation":"V","code":"RAT_3_","name":"Vereinigte Bundesversammlung","type":"B"},"name":"Redaktionskommission"},"function":null},{"id":3,"updated":"2013-11-25T11:49:40Z","entryDate":"2013-11-25T00:00:00Z","committee":{"id":3,"updated":"2010-12-26T13:06:13Z","abbreviation":"GPK","code":"KOM_3_","committeeNumber":3,"council":{"id":1,"updated":"2010-12-26T13:07:49Z","abbreviation":"NR","code":"RAT_1_","name":"Nationalrat","type":"N"},"name":"Geschäftsprüfungskommission NR"},"function":"Vizepräsident\/in"},{"id":2,"updated":"2013-01-07T11:23:38Z","entryDate":"2013-01-07T00:00:00Z","committee":{"id":997,"updated":"2013-01-07T11:20:42Z","abbreviation":"GPK-NS-FK-NS Agr Insieme","code":"KOM_997_","committeeNumber":997,"council":{"id":3,"updated":"2010-12-26T13:07:49Z","abbreviation":"V","code":"RAT_3_","name":"Vereinigte Bundesversammlung","type":"B"},"name":"Arbeitsgruppe Insieme der Geschäftsprüfungskommissionen und der Finanzkommissionen"},"function":null},{"id":4,"updated":"2015-04-20T09:45:36Z","entryDate":"2015-04-15T00:00:00Z","committee":{"id":975,"updated":"2012-04-16T10:41:39Z","abbreviation":"GPK-NS Agr Risikorep. BR","code":"KOM_975_","committeeNumber":975,"council":{"id":3,"updated":"2010-12-26T13:07:49Z","abbreviation":"V","code":"RAT_3_","name":"Vereinigte Bundesversammlung","type":"B"},"name":"Arbeitsgruppe Risikoreporting Bundesrat der Geschäftsprüfungskommissionen"},"function":null}],"concerns":[{"agency":"F","function":"M","name":"Advantis Versicherungsberatung AG, Zürich","organizationType":"Bei.","type":"AG"},{"agency":"F","function":"M","name":"aargauische stiftung suchthilfe ags, Aarau","organizationType":"Bei.","type":"Stift."},{"agency":"T","function":"P","name":"Fluck-Bernhard Stiftung, Wettingen","organizationType":"Sr.","type":"Stift."},{"agency":"T","function":"P","name":"Kappelerstiftung, Wettingen","organizationType":"Sr.","type":"Stift."},{"agency":"F","function":"M","name":"Swissaid, Bern","organizationType":"Sr.","type":"Stift."},{"agency":"F","function":"M","name":"Spirit of Bern","organizationType":"Bei.","type":"Ve."},{"agency":"T","function":"M","name":"Spitex Wettingen","organizationType":"V","type":"Ve."},{"agency":"T","function":"VP","name":"Regionales Pflegezentrum (RPB), Baden","organizationType":"GL, V","type":"-"}],"contact":{"emailPrivate":null,"emailWork":"yvonne.feri@parl.ch","faxPrivate":"+41 56 430 14 20","faxWork":null,"homepagePrivate":"www.yvonneferi.ch","homepageWork":null,"phoneMobilePrivate":"+41 79 781 20 43","phoneMobileWork":null,"phonePrivate":"+41 56 426 96 03","phoneWork":null},"councilMemberships":[{"id":0,"updated":"2011-11-07T16:35:07Z","entryDate":"2011-12-05T00:00:00Z","canton":"AG","cantonName":"Aargau","council":{"id":1,"updated":"2010-12-26T13:07:49Z","abbreviation":"NR","code":"RAT_1_","name":"Nationalrat","type":"N"}}],"displayLanguage":"de","domicile":{"canton":"AG","city":"Wettingen","addressLine":"Etzelmatt 6","zip":"5430"},"factionId":2,"gender":"f","homePlaces":[{"canton":"ZH","city":"Hedingen"}],"language":"de","mandate":"Legislative des Kantons: von 1998 bis 2008; Legislative der Gemeinde Wettingen: von Januar 2001 bis Dezember 2005; Exekutive der Gemeinde Wettingen: seit Januar 2006","numberOfChildren":2,"officialDenomination":"Feri Yvonne","partyId":12,"postalAddress":{"canton":null,"city":null,"addressLine":null,"zip":"0"},"professions":["Kauffrau"],"salutationLetter":"Frau Nationalrätin","salutationTitle":null,"workLanguage":"de"}