<?xml version="1.0" encoding="utf-8"?><councillor xmlns:i="http://www.w3.org/2001/XMLSchema-instance"><id>1156</id><updated>2015-05-17T21:18:19Z</updated><canton>Solothurn</canton><cantonName>SO</cantonName><council>N</council><faction>S</faction><factionName>Sozialdemokratische Fraktion</factionName><firstName>Bea</firstName><function>Mitglied</function><lastName>Heim</lastName><number>2601</number><party>SP</party><partyName>Sozialdemokratische Partei der Schweiz</partyName><active>true</active><additionalActivity>Co-Präsidentin der Parlamentarischen Gruppe für Altersfragen; Co-Präsidentin der Parlamentarischen Gruppe Biodiversität und Artenschutz; Co-Präsidentin der Parlamentarischen Gruppe Pflege</additionalActivity><birthDate>1946-04-07T00:00:00Z</birthDate><birthPlace><canton>AG</canton><city>Aarau</city></birthPlace><code i:nil="true" /><committeeMemberships><committeeMembership><id>0</id><updated>2010-12-26T13:07:50Z</updated><entryDate>2003-12-01T00:00:00Z</entryDate><leavingDate>2004-10-04T00:00:00Z</leavingDate><committee><id>3</id><updated>2010-12-26T13:06:13Z</updated><abbreviation>GPK</abbreviation><code>KOM_3_</code><committeeNumber>3</committeeNumber><council><id>1</id><updated>2010-12-26T13:07:49Z</updated><abbreviation>NR</abbreviation><code>RAT_1_</code><name>Nationalrat</name><type>N</type></council><name>Geschäftsprüfungskommission NR</name></committee><function i:nil="true" /></committeeMembership><committeeMembership><id>2</id><updated>2010-12-26T13:07:50Z</updated><entryDate>2004-10-05T00:00:00Z</entryDate><leavingDate>2007-12-02T00:00:00Z</leavingDate><committee><id>11</id><updated>2010-12-26T13:06:13Z</updated><abbreviation>SPK</abbreviation><code>KOM_11_</code><committeeNumber>11</committeeNumber><council><id>1</id><updated>2010-12-26T13:07:49Z</updated><abbreviation>NR</abbreviation><code>RAT_1_</code><name>Nationalrat</name><type>N</type></council><name>Staatspolitische Kommission NR</name></committee><function i:nil="true" /></committeeMembership><committeeMembership><id>3</id><updated>2011-11-01T08:56:54Z</updated><entryDate>2007-12-03T00:00:00Z</entryDate><leavingDate>2011-12-04T00:00:00Z</leavingDate><committee><id>13</id><updated>2012-03-26T08:58:31Z</updated><abbreviation>KöB</abbreviation><code>KOM_13_</code><committeeNumber>13</committeeNumber><council><id>1</id><updated>2010-12-26T13:07:49Z</updated><abbreviation>NR</abbreviation><code>RAT_1_</code><name>Nationalrat</name><type>N</type></council><name>Kommission für öffentliche Bauten NR</name></committee><function i:nil="true" /></committeeMembership><committeeMembership><id>4</id><updated>2011-11-01T08:56:54Z</updated><entryDate>2007-12-03T00:00:00Z</entryDate><leavingDate>2011-12-04T00:00:00Z</leavingDate><committee><id>11</id><updated>2010-12-26T13:06:13Z</updated><abbreviation>SPK</abbreviation><code>KOM_11_</code><committeeNumber>11</committeeNumber><council><id>1</id><updated>2010-12-26T13:07:49Z</updated><abbreviation>NR</abbreviation><code>RAT_1_</code><name>Nationalrat</name><type>N</type></council><name>Staatspolitische Kommission NR</name></committee><function i:nil="true" /></committeeMembership><committeeMembership><id>5</id><updated>2011-11-01T08:56:54Z</updated><entryDate>2007-12-03T00:00:00Z</entryDate><leavingDate>2011-12-04T00:00:00Z</leavingDate><committee><id>29</id><updated>2010-12-26T13:06:13Z</updated><abbreviation>BeK</abbreviation><code>KOM_29_</code><committeeNumber>29</committeeNumber><council><id>3</id><updated>2010-12-26T13:07:49Z</updated><abbreviation>V</abbreviation><code>RAT_3_</code><name>Vereinigte Bundesversammlung</name><type>B</type></council><name>Begnadigungskommission</name></committee><function i:nil="true" /></committeeMembership><committeeMembership><id>8</id><updated>2011-11-01T08:56:54Z</updated><entryDate>2009-03-12T00:00:00Z</entryDate><leavingDate>2011-12-04T00:00:00Z</leavingDate><committee><id>2</id><updated>2010-12-26T13:06:13Z</updated><abbreviation>FK</abbreviation><code>KOM_2_</code><committeeNumber>2</committeeNumber><council><id>1</id><updated>2010-12-26T13:07:49Z</updated><abbreviation>NR</abbreviation><code>RAT_1_</code><name>Nationalrat</name><type>N</type></council><name>Finanzkommission NR</name></committee><function i:nil="true" /></committeeMembership><committeeMembership><id>9</id><updated>2011-12-15T15:55:20Z</updated><entryDate>2011-12-15T00:00:00Z</entryDate><committee><id>11</id><updated>2010-12-26T13:06:13Z</updated><abbreviation>SPK</abbreviation><code>KOM_11_</code><committeeNumber>11</committeeNumber><council><id>1</id><updated>2010-12-26T13:07:49Z</updated><abbreviation>NR</abbreviation><code>RAT_1_</code><name>Nationalrat</name><type>N</type></council><name>Staatspolitische Kommission NR</name></committee><function i:nil="true" /></committeeMembership><committeeMembership><id>10</id><updated>2011-12-15T15:42:49Z</updated><entryDate>2011-12-15T00:00:00Z</entryDate><committee><id>6</id><updated>2010-12-26T13:06:13Z</updated><abbreviation>SGK</abbreviation><code>KOM_6_</code><committeeNumber>6</committeeNumber><council><id>1</id><updated>2010-12-26T13:07:49Z</updated><abbreviation>NR</abbreviation><code>RAT_1_</code><name>Nationalrat</name><type>N</type></council><name>Kommission für soziale Sicherheit und Gesundheit NR</name></committee><function i:nil="true" /></committeeMembership><committeeMembership><id>1</id><updated>2010-12-26T13:07:50Z</updated><entryDate>2004-02-25T00:00:00Z</entryDate><leavingDate>2004-06-16T00:00:00Z</leavingDate><committee><id>600</id><updated>2012-03-28T15:48:18Z</updated><abbreviation>04.012-NR</abbreviation><code>KOM_600_</code><committeeNumber>600</committeeNumber><council><id>1</id><updated>2010-12-26T13:07:49Z</updated><abbreviation>NR</abbreviation><code>RAT_1_</code><name>Nationalrat</name><type>N</type></council><name>Kommission 04.012-NR</name></committee><function i:nil="true" /></committeeMembership><committeeMembership><id>6</id><updated>2011-11-01T08:56:54Z</updated><entryDate>2007-12-03T00:00:00Z</entryDate><leavingDate>2011-12-04T00:00:00Z</leavingDate><committee><id>596</id><updated>2012-03-28T16:09:02Z</updated><abbreviation>RehaKo</abbreviation><code>KOM_596_</code><committeeNumber>596</committeeNumber><council><id>3</id><updated>2010-12-26T13:07:49Z</updated><abbreviation>V</abbreviation><code>RAT_3_</code><name>Vereinigte Bundesversammlung</name><type>B</type></council><name>Rehabilitierungskommission V</name></committee><function i:nil="true" /></committeeMembership><committeeMembership><id>7</id><updated>2010-12-26T13:07:50Z</updated><entryDate>2008-02-15T00:00:00Z</entryDate><leavingDate>2008-10-03T00:00:00Z</leavingDate><committee><id>713</id><updated>2012-02-07T08:48:09Z</updated><abbreviation>08.007-NR</abbreviation><code>KOM_713_</code><committeeNumber>713</committeeNumber><council><id>1</id><updated>2010-12-26T13:07:49Z</updated><abbreviation>NR</abbreviation><code>RAT_1_</code><name>Nationalrat</name><type>N</type></council><name>Kommission 08.007-NR</name></committee><function i:nil="true" /></committeeMembership><committeeMembership><id>11</id><updated>2014-10-02T14:53:18Z</updated><entryDate>2013-12-12T00:00:00Z</entryDate><leavingDate>2014-09-30T00:00:00Z</leavingDate><committee><id>1026</id><updated>2014-10-02T14:53:10Z</updated><abbreviation>13.092</abbreviation><code>KOM_1026_</code><committeeNumber>1026</committeeNumber><council><id>1</id><updated>2010-12-26T13:07:49Z</updated><abbreviation>NR</abbreviation><code>RAT_1_</code><name>Nationalrat</name><type>N</type></council><name>Kommission - 13.092 NR</name></committee><function i:nil="true" /></committeeMembership></committeeMemberships><concerns><concern><agency>F</agency><function>M</function><name>Albert Grütter-Schlatter-Stiftung, Solothurn</name><organizationType>Sr.</organizationType><type>Stift.</type></concern><concern><agency>F</agency><function>M</function><name>Keradonum Stiftung Hornhautbank, Olten</name><organizationType>Sr.</organizationType><type>Stift.</type></concern><concern><agency>F</agency><function>P</function><name>Pro Senectute Kanton Solothurn, Solothurn</name><organizationType>Sr.</organizationType><type>Stift.</type></concern><concern><agency>F</agency><function>P</function><name>Dachverband Schuldenberatung Schweiz</name><organizationType>V</organizationType><type>Ve.</type></concern><concern><agency>F</agency><function>M</function><name>IG Pro VEBO und INSOS, Oensingen</name><organizationType>V</organizationType><type>Ve.</type></concern><concern><agency>F</agency><function>P</function><name>IGoeV Schweiz, Interessengemeinschaft öffentlicher Verkehr</name><organizationType>V</organizationType><type>Ve.</type></concern><concern><agency>F</agency><function>M</function><name>Interessengemeinschaft öffentliche Arbeitsplätze (IGöffA), Olten</name><organizationType>V</organizationType><type>Ve.</type></concern><concern><agency>F</agency><function>M</function><name>Neue Europäische Bewegung Schweiz (nebs), Bern</name><organizationType>V</organizationType><type>Ve.</type></concern><concern><agency>F</agency><function>M</function><name>Palliative Care Netzwerk Kanton Solothurn, Solothurn</name><organizationType>V</organizationType><type>Ve.</type></concern><concern><agency>F</agency><function>M</function><name>Pro Natura Solothurn, Solothurn</name><organizationType>-</organizationType><type>Ve.</type></concern><concern><agency>F</agency><function>M</function><name>Schweizerische Vereinigung zum Schutz der kleinen und mittleren Bauern (VKMB), Bern</name><organizationType>-</organizationType><type>Ve.</type></concern><concern><agency>F</agency><function>M</function><name>Schweizerischer Eisenbahn- und Verkehrspersonal-Verband (SEV)</name><organizationType>-</organizationType><type>Ve.</type></concern><concern><agency>F</agency><function>P</function><name>Spital Club Solothurn</name><organizationType>V</organizationType><type>Ve.</type></concern><concern><agency>F</agency><function>M</function><name>Staatspersonalverband Kanton Solothurn</name><organizationType>-</organizationType><type>Ve.</type></concern><concern><agency>F</agency><function>M</function><name>VCS Kanton Solothurn</name><organizationType>-</organizationType><type>Ve.</type></concern><concern><agency>F</agency><function>M</function><name>Vereinigung Solothurnischer Musikschulen, Solothurn</name><organizationType>-</organizationType><type>Ve.</type></concern><concern><agency>F</agency><function>M</function><name>Lehrerinnen- und Lehrerverband Kanton Solothurn (LSO)</name><organizationType>-</organizationType><type>-</type></concern></concerns><contact><emailPrivate i:nil="true" /><emailWork>bea.heim@parl.ch</emailWork><faxPrivate>+41 62 295 23 14</faxPrivate><faxWork i:nil="true" /><homepagePrivate>www.bea-heim.ch</homepagePrivate><homepageWork i:nil="true" /><phoneMobilePrivate>+41 79 790 52 03</phoneMobilePrivate><phoneMobileWork i:nil="true" /><phonePrivate>+41 62 295 23 14</phonePrivate><phoneWork i:nil="true" /></contact><councilMemberships><councilMembership><id>0</id><updated>2012-03-22T14:52:06Z</updated><entryDate>2003-12-01T00:00:00Z</entryDate><leavingDate>2007-12-02T00:00:00Z</leavingDate><canton>SO</canton><cantonName>Solothurn</cantonName><council><id>1</id><updated>2010-12-26T13:07:49Z</updated><abbreviation>NR</abbreviation><code>RAT_1_</code><name>Nationalrat</name><type>N</type></council></councilMembership><councilMembership><id>1</id><updated>2012-03-22T14:52:15Z</updated><entryDate>2007-12-03T00:00:00Z</entryDate><leavingDate>2011-12-04T00:00:00Z</leavingDate><canton>SO</canton><cantonName>Solothurn</cantonName><council><id>1</id><updated>2010-12-26T13:07:49Z</updated><abbreviation>NR</abbreviation><code>RAT_1_</code><name>Nationalrat</name><type>N</type></council></councilMembership><councilMembership><id>2</id><updated>2011-11-02T08:10:30Z</updated><entryDate>2011-12-05T00:00:00Z</entryDate><canton>SO</canton><cantonName>Solothurn</cantonName><council><id>1</id><updated>2010-12-26T13:07:49Z</updated><abbreviation>NR</abbreviation><code>RAT_1_</code><name>Nationalrat</name><type>N</type></council></councilMembership></councilMemberships><displayLanguage>de</displayLanguage><domicile><canton>SO</canton><city>Starrkirch-Wil</city><addressLine>Untere Kohliweidstrasse 27</addressLine><zip>4656</zip></domicile><factionId>2</factionId><gender>f</gender><homePlaces><homePlace><canton>SO</canton><city>Neuendorf</city></homePlace><homePlace><canton>SO</canton><city>Olten</city></homePlace><homePlace><canton>AR</canton><city>Walzenhausen</city></homePlace></homePlaces><language>de</language><mandate>Legislative des Kantons (Kantonsrätin): von 1989 bis Januar 2004; Kantonsratspräsidentin: 1999</mandate><maritalStatus>verheiratet</maritalStatus><numberOfChildren>3</numberOfChildren><officialDenomination>Heim</officialDenomination><partyId>12</partyId><postalAddress><canton i:nil="true" /><city i:nil="true" /><addressLine i:nil="true" /><zip>0</zip></postalAddress><professions><profession>Rhythmik- und Heilpädagogin</profession></professions><salutationLetter>Frau Nationalrätin</salutationLetter><salutationTitle i:nil="true" /><workLanguage>de</workLanguage></councillor>