<?xml version="1.0" encoding="utf-8"?><councillor xmlns:i="http://www.w3.org/2001/XMLSchema-instance"><id>1560</id><updated>2015-05-17T21:18:19Z</updated><canton>Glarus</canton><cantonName>GL</cantonName><council>S</council><firstName>Leonhard</firstName><lastName>Blumer</lastName><active>false</active><birthDate>1844-05-28T00:00:00Z</birthDate><code i:nil="true" /><committeeMemberships /><concerns /><councilMemberships><councilMembership><id>0</id><updated>2011-01-06T11:34:34Z</updated><entryDate>1893-06-05T00:00:00Z</entryDate><leavingDate>1905-10-21T00:00:00Z</leavingDate><canton>GL</canton><cantonName>Glarus</cantonName><council><id>2</id><updated>2010-12-26T13:07:49Z</updated><abbreviation>SR</abbreviation><code>RAT_2_</code><name>Ständerat</name><type>S</type></council></councilMembership></councilMemberships><dateOfDeath>1905-10-21T00:00:00Z</dateOfDeath><displayLanguage>de</displayLanguage><gender>m</gender><homePlaces><homePlace><canton>GL</canton><city>Engi</city></homePlace></homePlaces><officialDenomination>Blumer Leonhard</officialDenomination><professions /><salutationLetter i:nil="true" /><salutationTitle i:nil="true" /></councillor>