<?xml version="1.0" encoding="utf-8"?><councillor xmlns:i="http://www.w3.org/2001/XMLSchema-instance"><id>215</id><updated>2015-05-17T21:18:19Z</updated><canton>Zürich</canton><cantonName>ZH</cantonName><council>N</council><firstName>Hans</firstName><lastName>Steffen</lastName><number>2175</number><active>false</active><birthDate>1931-09-29T00:00:00Z</birthDate><birthPlace><canton>ZH</canton><city>Zürich</city></birthPlace><code i:nil="true" /><committeeMemberships><committeeMembership><id>0</id><updated>2010-12-26T13:07:50Z</updated><entryDate>1996-12-12T00:00:00Z</entryDate><leavingDate>1998-12-18T00:00:00Z</leavingDate><committee><id>1</id><updated>2010-12-26T13:06:13Z</updated><abbreviation>Bü</abbreviation><code>KOM_1_</code><committeeNumber>1</committeeNumber><council><id>1</id><updated>2010-12-26T13:07:49Z</updated><abbreviation>NR</abbreviation><code>RAT_1_</code><name>Nationalrat</name><type>N</type></council><name>Büro NR</name></committee><function>Fraktionspräsident/in</function></committeeMembership><committeeMembership><id>1</id><updated>2010-12-26T13:07:50Z</updated><entryDate>1996-12-13T00:00:00Z</entryDate><leavingDate>1997-03-23T00:00:00Z</leavingDate><committee><id>3</id><updated>2010-12-26T13:06:13Z</updated><abbreviation>GPK</abbreviation><code>KOM_3_</code><committeeNumber>3</committeeNumber><council><id>1</id><updated>2010-12-26T13:07:49Z</updated><abbreviation>NR</abbreviation><code>RAT_1_</code><name>Nationalrat</name><type>N</type></council><name>Geschäftsprüfungskommission NR</name></committee><function i:nil="true" /></committeeMembership><committeeMembership><id>2</id><updated>2010-12-26T13:07:50Z</updated><entryDate>1997-10-10T00:00:00Z</entryDate><leavingDate>1999-12-05T00:00:00Z</leavingDate><committee><id>11</id><updated>2010-12-26T13:06:13Z</updated><abbreviation>SPK</abbreviation><code>KOM_11_</code><committeeNumber>11</committeeNumber><council><id>1</id><updated>2010-12-26T13:07:49Z</updated><abbreviation>NR</abbreviation><code>RAT_1_</code><name>Nationalrat</name><type>N</type></council><name>Staatspolitische Kommission NR</name></committee><function i:nil="true" /></committeeMembership></committeeMemberships><concerns /><contact><emailPrivate>hans.steffen@bluewin.ch</emailPrivate><emailWork i:nil="true" /><faxPrivate i:nil="true" /><faxWork i:nil="true" /><homepagePrivate i:nil="true" /><homepageWork i:nil="true" /><phoneMobilePrivate i:nil="true" /><phoneMobileWork i:nil="true" /><phonePrivate i:nil="true" /><phoneWork i:nil="true" /></contact><councilMemberships><councilMembership><id>0</id><updated>2013-03-25T15:10:31Z</updated><entryDate>1985-02-04T00:00:00Z</entryDate><leavingDate>1995-12-03T00:00:00Z</leavingDate><canton>ZH</canton><cantonName>Zürich</cantonName><council><id>1</id><updated>2010-12-26T13:07:49Z</updated><abbreviation>NR</abbreviation><code>RAT_1_</code><name>Nationalrat</name><type>N</type></council></councilMembership><councilMembership><id>1</id><updated>2013-03-25T16:14:20Z</updated><entryDate>1995-12-04T00:00:00Z</entryDate><leavingDate>1999-12-05T00:00:00Z</leavingDate><canton>ZH</canton><cantonName>Zürich</cantonName><council><id>1</id><updated>2010-12-26T13:07:49Z</updated><abbreviation>NR</abbreviation><code>RAT_1_</code><name>Nationalrat</name><type>N</type></council></councilMembership></councilMemberships><displayLanguage>de</displayLanguage><domicile><canton i:nil="true" /><city i:nil="true" /><addressLine i:nil="true" /><zip>0</zip></domicile><gender>m</gender><homePlaces><homePlace><canton>ZH</canton><city>Fischenthal</city></homePlace><homePlace><canton>ZH</canton><city>Kloten</city></homePlace><homePlace><canton>ZH</canton><city>Zürich</city></homePlace></homePlaces><language>de</language><mandate>Gemeinderat von 1964 bis 1973</mandate><maritalStatus>verheiratet</maritalStatus><militaryGrade>Oberleutnant</militaryGrade><numberOfChildren>2</numberOfChildren><officialDenomination>Steffen</officialDenomination><postalAddress><canton>ZH</canton><city>Fischenthal</city><addressLine>Widenreitistrasse 11</addressLine><zip>8497</zip></postalAddress><professions><profession>Politiker</profession><profession>Realschullehrer</profession></professions><salutationLetter>Herr</salutationLetter><salutationTitle i:nil="true" /><workLanguage>de</workLanguage></councillor>