<?xml version="1.0" encoding="utf-8"?><councillor xmlns:i="http://www.w3.org/2001/XMLSchema-instance"><id>2387</id><updated>2015-05-17T21:18:19Z</updated><canton>Basel-Stadt</canton><cantonName>BS</cantonName><council>N</council><firstName>Max</firstName><lastName>Imboden</lastName><active>false</active><birthDate>1915-06-19T00:00:00Z</birthDate><code i:nil="true" /><committeeMemberships /><concerns /><councilMemberships><councilMembership><id>0</id><updated>2010-12-26T13:07:53Z</updated><entryDate>1965-06-14T00:00:00Z</entryDate><leavingDate>1967-12-03T00:00:00Z</leavingDate><canton>BS</canton><cantonName>Basel-Stadt</cantonName><council><id>1</id><updated>2010-12-26T13:07:49Z</updated><abbreviation>NR</abbreviation><code>RAT_1_</code><name>Nationalrat</name><type>N</type></council></councilMembership></councilMemberships><dateOfDeath>1969-04-07T00:00:00Z</dateOfDeath><displayLanguage>de</displayLanguage><gender>m</gender><homePlaces><homePlace><canton>SG</canton><city>St. Gallen</city></homePlace><homePlace><canton>BE</canton><city>Unterseen</city></homePlace></homePlaces><officialDenomination i:nil="true" /><professions /><salutationLetter i:nil="true" /><salutationTitle i:nil="true" /></councillor>