<?xml version="1.0" encoding="utf-8"?><councillor xmlns:i="http://www.w3.org/2001/XMLSchema-instance"><id>4066</id><updated>2015-06-09T13:13:08Z</updated><canton>Zürich</canton><cantonName>ZH</cantonName><council>N</council><faction>BD</faction><factionName>Fraktion BD</factionName><firstName>Rosmarie</firstName><function>Präsident/in</function><lastName>Quadranti</lastName><number>2779</number><party>BDP</party><partyName>Bürgerlich-Demokratische Partei Schweiz</partyName><active>true</active><additionalActivity>Co-Präsidentin der Parlamentarischen Damen Sportgruppe; Co-Präsidentin der Parlamentarischen Frauengruppe; Co-Präsidentin der Parlamentarischen Gruppe MINT-Förderung als Beitrag zur Behebung des Fachkräftemangels; Co-Präsidentin der Parlamentarischen Gruppe Mehrsprachigkeit</additionalActivity><additionalMandate>Vizepräsidentin BDP Volketswil: seit Januar 2010; Präsidentin Bildungskommission BDP Kanton Zürich: seit Januar 2011; Mitglied des Vorstandes BDP Kanton Zürich: seit Januar 2011; Mitglied der Geschäftsleitung der BDP Schweiz: seit Mai 2012</additionalMandate><birthDate>1957-07-18T00:00:00Z</birthDate><birthPlace><canton>LU</canton><city>Luzern</city></birthPlace><code i:nil="true" /><committeeMemberships><committeeMembership><id>0</id><updated>2011-12-15T15:40:41Z</updated><entryDate>2011-12-15T00:00:00Z</entryDate><committee><id>5</id><updated>2010-12-26T13:06:13Z</updated><abbreviation>WBK</abbreviation><code>KOM_5_</code><committeeNumber>5</committeeNumber><council><id>1</id><updated>2010-12-26T13:07:49Z</updated><abbreviation>NR</abbreviation><code>RAT_1_</code><name>Nationalrat</name><type>N</type></council><name>Kommission für Wissenschaft, Bildung und Kultur NR</name></committee><function i:nil="true" /></committeeMembership><committeeMembership><id>1</id><updated>2014-12-01T13:32:43Z</updated><entryDate>2011-12-15T00:00:00Z</entryDate><leavingDate>2014-11-24T00:00:00Z</leavingDate><committee><id>2</id><updated>2010-12-26T13:06:13Z</updated><abbreviation>FK</abbreviation><code>KOM_2_</code><committeeNumber>2</committeeNumber><council><id>1</id><updated>2010-12-26T13:07:49Z</updated><abbreviation>NR</abbreviation><code>RAT_1_</code><name>Nationalrat</name><type>N</type></council><name>Finanzkommission NR</name></committee><function i:nil="true" /></committeeMembership><committeeMembership><id>3</id><updated>2014-12-01T13:33:11Z</updated><entryDate>2014-11-24T00:00:00Z</entryDate><committee><id>4</id><updated>2010-12-26T13:06:13Z</updated><abbreviation>APK</abbreviation><code>KOM_4_</code><committeeNumber>4</committeeNumber><council><id>1</id><updated>2010-12-26T13:07:49Z</updated><abbreviation>NR</abbreviation><code>RAT_1_</code><name>Nationalrat</name><type>N</type></council><name>Aussenpolitische Kommission NR</name></committee><function i:nil="true" /></committeeMembership><committeeMembership><id>4</id><updated>2015-03-18T08:52:48Z</updated><entryDate>2015-03-23T00:00:00Z</entryDate><committee><id>1</id><updated>2010-12-26T13:06:13Z</updated><abbreviation>Bü</abbreviation><code>KOM_1_</code><committeeNumber>1</committeeNumber><council><id>1</id><updated>2010-12-26T13:07:49Z</updated><abbreviation>NR</abbreviation><code>RAT_1_</code><name>Nationalrat</name><type>N</type></council><name>Büro NR</name></committee><function>Fraktionspräsident/in</function></committeeMembership><committeeMembership><id>2</id><updated>2013-01-07T11:23:38Z</updated><entryDate>2013-01-07T00:00:00Z</entryDate><committee><id>997</id><updated>2013-01-07T11:20:42Z</updated><abbreviation>GPK-NS-FK-NS Agr Insieme</abbreviation><code>KOM_997_</code><committeeNumber>997</committeeNumber><council><id>3</id><updated>2010-12-26T13:07:49Z</updated><abbreviation>V</abbreviation><code>RAT_3_</code><name>Vereinigte Bundesversammlung</name><type>B</type></council><name>Arbeitsgruppe Insieme der Geschäftsprüfungskommissionen und der Finanzkommissionen</name></committee><function i:nil="true" /></committeeMembership></committeeMemberships><concerns><concern><agency>T</agency><function>M</function><name>Zentrum für Gehör und Sprache, Zürich (Zentrumrat)</name><organizationType>-</organizationType><type>Anst.</type></concern><concern><agency>F</agency><function>M</function><name>Beratende Kommission für internationale Entwicklungszusammenarbeit</name><organizationType>-</organizationType><type>EidgKomm</type></concern><concern><agency>F</agency><function>M</function><name>Gen Suisse - Schweizerische Stiftung für eine verantwortungsvolle Gentechnik, Bern</name><organizationType>Sr.</organizationType><type>Stift.</type></concern><concern><agency>F</agency><function>P</function><name>Stiftung Kinderdorf Pestalozzi, Trogen</name><organizationType>Sr.</organizationType><type>Stift.</type></concern><concern><agency>F</agency><function>M</function><name>Stiftung Schweizerischer Privatschulen, Bern</name><organizationType>Sr.</organizationType><type>Stift.</type></concern><concern><agency>F</agency><function>M</function><name>Zürcher Stiftung für Gefangenen und Entlassenenfürsorge ZSGE, Zürich</name><organizationType>Sr.</organizationType><type>Stift.</type></concern><concern><agency>F</agency><function>M</function><name>Fachstelle Fehlgeburt und perinataler Kindstod</name><organizationType>V</organizationType><type>Ve.</type></concern><concern><agency>F</agency><function>M</function><name>Gesellschaft Schweiz-Albanien, Goldach</name><organizationType>Bei.</organizationType><type>Ve.</type></concern><concern><agency>F</agency><function>P</function><name>Verband Kibesuisse, Kinderbetreuung Schweiz, Zürich</name><organizationType>V</organizationType><type>Ve.</type></concern><concern><agency>F</agency><function>M</function><name>Verband Zürcher Schulpräsidien (VZS), Zürich</name><organizationType>V</organizationType><type>Ve.</type></concern><concern><agency>F</agency><function>VP</function><name>Verein Prävention und Drogenfragen, Uster</name><organizationType>V</organizationType><type>Ve.</type></concern><concern><agency>F</agency><function>M</function><name>Zürich Erneuerbar (Verein für Energieeffizienz und erneuerbare Energien), Zürich</name><organizationType>V</organizationType><type>Ve.</type></concern><concern><agency>F</agency><function>M</function><name>Schweizerisches Kompetenzzentrum für Menschenrechte (SKMR)</name><organizationType>Bei.</organizationType><type>-</type></concern></concerns><contact><emailPrivate i:nil="true" /><emailWork>rosmarie.quadranti@parl.ch</emailWork><faxPrivate i:nil="true" /><faxWork i:nil="true" /><homepagePrivate>www.rosmarie-quadranti.ch</homepagePrivate><homepageWork i:nil="true" /><phoneMobilePrivate i:nil="true" /><phoneMobileWork i:nil="true" /><phonePrivate i:nil="true" /><phoneWork i:nil="true" /></contact><councilMemberships><councilMembership><id>0</id><updated>2011-11-07T15:39:37Z</updated><entryDate>2011-12-05T00:00:00Z</entryDate><canton>ZH</canton><cantonName>Zürich</cantonName><council><id>1</id><updated>2010-12-26T13:07:49Z</updated><abbreviation>NR</abbreviation><code>RAT_1_</code><name>Nationalrat</name><type>N</type></council></councilMembership></councilMemberships><displayLanguage>de</displayLanguage><domicile><canton>ZH</canton><city>Volketswil</city><addressLine>Waldackerweg 11</addressLine><zip>8604</zip></domicile><factionId>136</factionId><gender>f</gender><homePlaces><homePlace><canton>ZH</canton><city>Volketswil</city></homePlace></homePlaces><language>de</language><mandate>Mitglied Schulpflege: von August 1994 bis Dezember 1999; Präsidentin Schulpflege Volketswil: seit 2000; Regionale Jugendkommission: von 2004 bis Dezember 2011</mandate><maritalStatus>verheiratet</maritalStatus><numberOfChildren>3</numberOfChildren><officialDenomination>Quadranti</officialDenomination><partyId>1551</partyId><postalAddress><canton i:nil="true" /><city i:nil="true" /><addressLine i:nil="true" /><zip>0</zip></postalAddress><professions><profession>Kauffrau</profession></professions><salutationLetter>Frau Nationalrätin</salutationLetter><salutationTitle i:nil="true" /><workLanguage>de</workLanguage></councillor>