<?xml version="1.0" encoding="utf-8"?><councillor xmlns:i="http://www.w3.org/2001/XMLSchema-instance"><id>4084</id><updated>2015-05-17T21:18:19Z</updated><canton>Zug</canton><cantonName>ZG</cantonName><council>N</council><faction>RL</faction><factionName>FDP-Liberale Fraktion</factionName><firstName>Bruno</firstName><function>Mitglied</function><lastName>Pezzatti</lastName><number>2784</number><party>FDP-Liberale</party><partyName>FDP.Die Liberalen</partyName><active>true</active><additionalActivity>Vize-Präsident der Parlamentarische Gruppe Inlandbanken</additionalActivity><birthDate>1951-03-04T00:00:00Z</birthDate><birthPlace><canton>ZG</canton><city>Zug</city></birthPlace><code i:nil="true" /><committeeMemberships><committeeMembership><id>0</id><updated>2011-12-15T15:42:49Z</updated><entryDate>2011-12-15T00:00:00Z</entryDate><committee><id>6</id><updated>2010-12-26T13:06:13Z</updated><abbreviation>SGK</abbreviation><code>KOM_6_</code><committeeNumber>6</committeeNumber><council><id>1</id><updated>2010-12-26T13:07:49Z</updated><abbreviation>NR</abbreviation><code>RAT_1_</code><name>Nationalrat</name><type>N</type></council><name>Kommission für soziale Sicherheit und Gesundheit NR</name></committee><function i:nil="true" /></committeeMembership></committeeMemberships><concerns><concern><agency>F</agency><function>M</function><name>Kernkraftwerk Gösgen-Däniken AG, Däniken</name><organizationType>VR</organizationType><type>AG</type></concern><concern><agency>F</agency><function>M</function><name>IG biomedizinische Forschung und Innovation</name><organizationType>-</organizationType><type>EG</type></concern><concern><agency>F</agency><function>M</function><name>Informationsgruppe Erfrischungsgetränke</name><organizationType>V</organizationType><type>EG</type></concern><concern><agency>F</agency><function>P</function><name>Raiffeisenbank Menzingen-Neuheim, Menzingen</name><organizationType>Vw.</organizationType><type>Gen.</type></concern><concern><agency>F</agency><function>VP</function><name>Gen Suisse - Schweizerische Stiftung für eine verantwortungsvolle Gentechnik, Bern</name><organizationType>Sr.</organizationType><type>Stift.</type></concern><concern><agency>F</agency><function>P</function><name>Ausgleichskasse Verom, Schlieren</name><organizationType>V</organizationType><type>Ve.</type></concern><concern><agency>F</agency><function>M</function><name>Connecta, Integration geistig Behinderter im Arbeitsmarkt</name><organizationType>-</organizationType><type>Ve.</type></concern><concern><agency>F</agency><function>M</function><name>Freunde des Morgantenschiessens</name><organizationType>-</organizationType><type>Ve.</type></concern><concern><agency>F</agency><function>M</function><name>Leichtathletik Club Zug</name><organizationType>-</organizationType><type>Ve.</type></concern><concern><agency>F</agency><function>M</function><name>Orientierungs-Lauf-Verein Zug</name><organizationType>-</organizationType><type>Ve.</type></concern><concern><agency>F</agency><function>M</function><name>Raiffeisenbanken Kanton Zug</name><organizationType>V</organizationType><type>Ve.</type></concern><concern><agency>F</agency><function>M</function><name>Rotary Club Ägeri-Menzingen</name><organizationType>-</organizationType><type>Ve.</type></concern><concern><agency>F</agency><function>M</function><name>Schweizer Obstverband (SOV)</name><organizationType>V</organizationType><type>Ve.</type></concern><concern><agency>F</agency><function>M</function><name>Vorstand parlam. Gruppe Gastrosuisse</name><organizationType>V</organizationType><type>Ve.</type></concern><concern><agency>F</agency><function>M</function><name>Weinfreunde Menzingen</name><organizationType>-</organizationType><type>Ve.</type></concern><concern><agency>F</agency><function>M</function><name>Groupe Mutuel, Groupe de réflexion santé</name><organizationType>Bei.</organizationType><type>-</type></concern></concerns><contact><emailPrivate i:nil="true" /><emailWork>bruno.pezzatti@parl.ch</emailWork><faxPrivate i:nil="true" /><faxWork i:nil="true" /><homepagePrivate i:nil="true" /><homepageWork i:nil="true" /><phoneMobilePrivate i:nil="true" /><phoneMobileWork i:nil="true" /><phonePrivate i:nil="true" /><phoneWork i:nil="true" /></contact><councilMemberships><councilMembership><id>0</id><updated>2011-11-09T08:45:02Z</updated><entryDate>2011-12-05T00:00:00Z</entryDate><canton>ZG</canton><cantonName>Zug</cantonName><council><id>1</id><updated>2010-12-26T13:07:49Z</updated><abbreviation>NR</abbreviation><code>RAT_1_</code><name>Nationalrat</name><type>N</type></council></councilMembership></councilMemberships><displayLanguage>de</displayLanguage><domicile><canton i:nil="true" /><city i:nil="true" /><addressLine i:nil="true" /><zip>0</zip></domicile><factionId>1</factionId><gender>m</gender><homePlaces><homePlace><canton>TI</canton><city>Torricella-Taverne</city></homePlace></homePlaces><language>de</language><mandate>Legislative des Kantons (Kantonsrat): von 1998 bis 2010; Kantonsratspräsident: von Januar 2009 bis Dezember 2010</mandate><maritalStatus>verheiratet</maritalStatus><militaryGrade>Gefreiter</militaryGrade><numberOfChildren>2</numberOfChildren><officialDenomination>Pezzatti</officialDenomination><partyId>15</partyId><postalAddress><canton>ZG</canton><city>Zug</city><addressLine>Baarerstrasse 88</addressLine><company>c/o Schweizer Obstverband</company><zip>6300</zip></postalAddress><professions><profession>Vorstandsmitglied Schweizer Obstverband</profession></professions><salutationLetter>Herr Nationalrat</salutationLetter><salutationTitle i:nil="true" /><title>dipl. Ing. Agr. ETH</title><workLanguage>de</workLanguage></councillor>