<?xml version="1.0" encoding="utf-8"?><councillor xmlns:i="http://www.w3.org/2001/XMLSchema-instance"><id>4099</id><updated>2015-05-17T21:18:19Z</updated><canton>Basel-Stadt</canton><cantonName>BS</cantonName><council>N</council><faction>CE</faction><factionName>Fraktion CVP-EVP</factionName><firstName>Markus</firstName><function>Mitglied</function><lastName>Lehmann</lastName><number>3011</number><party>CVP</party><partyName>Christlichdemokratische Volkspartei der Schweiz</partyName><active>true</active><additionalActivity>Co-Präsident der Parlamentarischen Gruppe Fanpolitik in der Schweiz</additionalActivity><additionalMandate>Präsident der CVP Basel-Stadt: seit März 2011</additionalMandate><birthDate>1955-05-27T00:00:00Z</birthDate><birthPlace><canton>BS</canton><city>Basel</city></birthPlace><code i:nil="true" /><committeeMemberships><committeeMembership><id>0</id><updated>2013-12-12T16:41:17Z</updated><entryDate>2011-12-15T00:00:00Z</entryDate><leavingDate>2013-12-11T00:00:00Z</leavingDate><committee><id>12</id><updated>2010-12-26T13:06:13Z</updated><abbreviation>RK</abbreviation><code>KOM_12_</code><committeeNumber>12</committeeNumber><council><id>1</id><updated>2010-12-26T13:07:49Z</updated><abbreviation>NR</abbreviation><code>RAT_1_</code><name>Nationalrat</name><type>N</type></council><name>Kommission für Rechtsfragen NR</name></committee><function i:nil="true" /></committeeMembership><committeeMembership><id>2</id><updated>2013-12-12T16:40:28Z</updated><entryDate>2013-12-12T00:00:00Z</entryDate><committee><id>9</id><updated>2010-12-26T13:06:13Z</updated><abbreviation>KVF</abbreviation><code>KOM_9_</code><committeeNumber>9</committeeNumber><council><id>1</id><updated>2010-12-26T13:07:49Z</updated><abbreviation>NR</abbreviation><code>RAT_1_</code><name>Nationalrat</name><type>N</type></council><name>Kommission für Verkehr und Fernmeldewesen NR</name></committee><function i:nil="true" /></committeeMembership><committeeMembership><id>1</id><updated>2013-02-05T10:55:44Z</updated><entryDate>2011-12-15T00:00:00Z</entryDate><leavingDate>2012-06-15T00:00:00Z</leavingDate><committee><id>938</id><updated>2013-02-05T10:55:43Z</updated><abbreviation>12.008-NR</abbreviation><code>KOM_938_</code><committeeNumber>938</committeeNumber><council><id>1</id><updated>2010-12-26T13:07:49Z</updated><abbreviation>NR</abbreviation><code>RAT_1_</code><name>Nationalrat</name><type>N</type></council><name>Kommission 12.008-NR</name></committee><function i:nil="true" /></committeeMembership></committeeMemberships><concerns><concern><agency>F</agency><function>Gf.</function><name>Balrisk Versicherungsbroker AG, Binningen</name><organizationType>VR</organizationType><type>AG</type></concern><concern><agency>F</agency><function>P</function><name>Genossenschaft St. Jakob-Park, Basel</name><organizationType>V</organizationType><type>Gen.</type></concern><concern><agency>T</agency><function>M</function><name>Christoph Merian Stiftung (CMS), Basel</name><organizationType>Sr.</organizationType><type>Stift.</type></concern><concern><agency>F</agency><function>M</function><name>Sportmuseum Schweiz, Basel</name><organizationType>Sr.</organizationType><type>Stift.</type></concern><concern><agency>F</agency><function>M</function><name>Stiftungskommission der Pensionskasse der Basler Kantonalbank</name><organizationType>Sr.</organizationType><type>Stift.</type></concern></concerns><contact><emailPrivate i:nil="true" /><emailWork i:nil="true" /><faxPrivate i:nil="true" /><faxWork>+41 61 268 90 95</faxWork><homepagePrivate i:nil="true" /><homepageWork>www.lehmann-markus.ch</homepageWork><phoneMobilePrivate i:nil="true" /><phoneMobileWork i:nil="true" /><phonePrivate>+41 61 322 06 83</phonePrivate><phoneWork>+41 61 268 90 90</phoneWork></contact><councilMemberships><councilMembership><id>0</id><updated>2011-11-11T16:59:35Z</updated><entryDate>2011-12-05T00:00:00Z</entryDate><canton>BS</canton><cantonName>Basel-Stadt</cantonName><council><id>1</id><updated>2010-12-26T13:07:49Z</updated><abbreviation>NR</abbreviation><code>RAT_1_</code><name>Nationalrat</name><type>N</type></council></councilMembership></councilMemberships><displayLanguage>de</displayLanguage><domicile><canton>BS</canton><city>Basel</city><addressLine>Dammerkirchstrasse 42</addressLine><zip>4056</zip></domicile><factionId>3</factionId><gender>m</gender><homePlaces><homePlace><canton>BS</canton><city>Basel</city></homePlace><homePlace><canton>SO</canton><city>Trimbach</city></homePlace></homePlaces><language>de</language><mandate>Legislative des Kantons (Grossrat): seit Februar 2009; Grossratspräsident: von Februar 2011 bis Januar 2012</mandate><maritalStatus>verheiratet</maritalStatus><numberOfChildren>2</numberOfChildren><officialDenomination>Lehmann</officialDenomination><partyId>14</partyId><postalAddress><canton>BS</canton><city>Basel</city><addressLine>Arnold-Böcklinstrasse 41</addressLine><company>Balrisk Versicherungsbroker AG</company><zip>4051</zip></postalAddress><professions><profession>Versicherungsbroker</profession></professions><salutationLetter>Herr Nationalrat</salutationLetter><salutationTitle i:nil="true" /><title>Eidg. dipl. Versicherungsfachmann</title><workLanguage>de</workLanguage></councillor>