<?xml version="1.0" encoding="utf-8"?><councillor xmlns:i="http://www.w3.org/2001/XMLSchema-instance"><id>805</id><updated>2015-05-17T21:18:19Z</updated><canton>Bern</canton><cantonName>BE</cantonName><council>S</council><firstName>Hans</firstName><lastName>Lauri</lastName><number>2568</number><active>false</active><birthDate>1944-10-26T00:00:00Z</birthDate><birthPlace><canton>BE</canton><city>Bern</city></birthPlace><code i:nil="true" /><committeeMemberships><committeeMembership><id>0</id><updated>2010-12-26T13:07:50Z</updated><entryDate>2001-06-13T00:00:00Z</entryDate><leavingDate>2003-11-30T00:00:00Z</leavingDate><committee><id>22</id><updated>2010-12-26T13:06:13Z</updated><abbreviation>KVF</abbreviation><code>KOM_22_</code><committeeNumber>22</committeeNumber><council><id>2</id><updated>2010-12-26T13:07:49Z</updated><abbreviation>SR</abbreviation><code>RAT_2_</code><name>Ständerat</name><type>S</type></council><name>Kommission für Verkehr und Fernmeldewesen SR</name></committee><function i:nil="true" /></committeeMembership><committeeMembership><id>1</id><updated>2010-12-26T13:07:50Z</updated><entryDate>2001-06-13T00:00:00Z</entryDate><leavingDate>2003-11-30T00:00:00Z</leavingDate><committee><id>18</id><updated>2010-12-26T13:06:13Z</updated><abbreviation>WBK</abbreviation><code>KOM_18_</code><committeeNumber>18</committeeNumber><council><id>2</id><updated>2010-12-26T13:07:49Z</updated><abbreviation>SR</abbreviation><code>RAT_2_</code><name>Ständerat</name><type>S</type></council><name>Kommission für Wissenschaft, Bildung und Kultur SR</name></committee><function i:nil="true" /></committeeMembership><committeeMembership><id>2</id><updated>2010-12-26T13:07:50Z</updated><entryDate>2001-06-13T00:00:00Z</entryDate><leavingDate>2002-10-03T00:00:00Z</leavingDate><committee><id>25</id><updated>2010-12-26T13:06:13Z</updated><abbreviation>RK</abbreviation><code>KOM_25_</code><committeeNumber>25</committeeNumber><council><id>2</id><updated>2010-12-26T13:07:49Z</updated><abbreviation>SR</abbreviation><code>RAT_2_</code><name>Ständerat</name><type>S</type></council><name>Kommission für Rechtsfragen SR</name></committee><function i:nil="true" /></committeeMembership><committeeMembership><id>3</id><updated>2010-12-26T13:07:50Z</updated><entryDate>2001-06-13T00:00:00Z</entryDate><leavingDate>2002-06-21T00:00:00Z</leavingDate><committee><id>16</id><updated>2010-12-26T13:06:13Z</updated><abbreviation>GPK</abbreviation><code>KOM_16_</code><committeeNumber>16</committeeNumber><council><id>2</id><updated>2010-12-26T13:07:49Z</updated><abbreviation>SR</abbreviation><code>RAT_2_</code><name>Ständerat</name><type>S</type></council><name>Geschäftsprüfungskommission SR</name></committee><function i:nil="true" /></committeeMembership><committeeMembership><id>5</id><updated>2010-12-26T13:07:50Z</updated><entryDate>2002-06-24T00:00:00Z</entryDate><leavingDate>2002-08-29T00:00:00Z</leavingDate><committee><id>15</id><updated>2010-12-26T13:06:13Z</updated><abbreviation>FK</abbreviation><code>KOM_15_</code><committeeNumber>15</committeeNumber><council><id>2</id><updated>2010-12-26T13:07:49Z</updated><abbreviation>SR</abbreviation><code>RAT_2_</code><name>Ständerat</name><type>S</type></council><name>Finanzkommission SR</name></committee><function i:nil="true" /></committeeMembership><committeeMembership><id>6</id><updated>2010-12-26T13:07:50Z</updated><entryDate>2002-08-30T00:00:00Z</entryDate><leavingDate>2003-11-30T00:00:00Z</leavingDate><committee><id>15</id><updated>2010-12-26T13:06:13Z</updated><abbreviation>FK</abbreviation><code>KOM_15_</code><committeeNumber>15</committeeNumber><council><id>2</id><updated>2010-12-26T13:07:49Z</updated><abbreviation>SR</abbreviation><code>RAT_2_</code><name>Ständerat</name><type>S</type></council><name>Finanzkommission SR</name></committee><function>Vizepräsident/in</function></committeeMembership><committeeMembership><id>9</id><updated>2010-12-26T13:07:50Z</updated><entryDate>2003-12-01T00:00:00Z</entryDate><leavingDate>2007-12-02T00:00:00Z</leavingDate><committee><id>29</id><updated>2010-12-26T13:06:13Z</updated><abbreviation>BeK</abbreviation><code>KOM_29_</code><committeeNumber>29</committeeNumber><council><id>3</id><updated>2010-12-26T13:07:49Z</updated><abbreviation>V</abbreviation><code>RAT_3_</code><name>Vereinigte Bundesversammlung</name><type>B</type></council><name>Begnadigungskommission</name></committee><function i:nil="true" /></committeeMembership><committeeMembership><id>12</id><updated>2010-12-26T13:07:50Z</updated><entryDate>2003-12-01T00:00:00Z</entryDate><leavingDate>2007-12-02T00:00:00Z</leavingDate><committee><id>23</id><updated>2010-12-26T13:06:13Z</updated><abbreviation>WAK</abbreviation><code>KOM_23_</code><committeeNumber>23</committeeNumber><council><id>2</id><updated>2010-12-26T13:07:49Z</updated><abbreviation>SR</abbreviation><code>RAT_2_</code><name>Ständerat</name><type>S</type></council><name>Kommission für Wirtschaft und Abgaben SR</name></committee><function i:nil="true" /></committeeMembership><committeeMembership><id>14</id><updated>2010-12-26T13:07:50Z</updated><entryDate>2003-12-01T00:00:00Z</entryDate><leavingDate>2005-11-27T00:00:00Z</leavingDate><committee><id>15</id><updated>2010-12-26T13:06:13Z</updated><abbreviation>FK</abbreviation><code>KOM_15_</code><committeeNumber>15</committeeNumber><council><id>2</id><updated>2010-12-26T13:07:49Z</updated><abbreviation>SR</abbreviation><code>RAT_2_</code><name>Ständerat</name><type>S</type></council><name>Finanzkommission SR</name></committee><function>Präsident/in</function></committeeMembership><committeeMembership><id>18</id><updated>2010-12-26T13:07:50Z</updated><entryDate>2005-11-28T00:00:00Z</entryDate><leavingDate>2007-12-02T00:00:00Z</leavingDate><committee><id>15</id><updated>2010-12-26T13:06:13Z</updated><abbreviation>FK</abbreviation><code>KOM_15_</code><committeeNumber>15</committeeNumber><council><id>2</id><updated>2010-12-26T13:07:49Z</updated><abbreviation>SR</abbreviation><code>RAT_2_</code><name>Ständerat</name><type>S</type></council><name>Finanzkommission SR</name></committee><function i:nil="true" /></committeeMembership><committeeMembership><id>4</id><updated>2010-12-26T13:07:50Z</updated><entryDate>2001-11-26T00:00:00Z</entryDate><leavingDate>2003-10-03T00:00:00Z</leavingDate><committee><id>483</id><updated>2012-03-28T16:08:38Z</updated><abbreviation>01.074-SR</abbreviation><code>KOM_483_</code><committeeNumber>483</committeeNumber><council><id>2</id><updated>2010-12-26T13:07:49Z</updated><abbreviation>SR</abbreviation><code>RAT_2_</code><name>Ständerat</name><type>S</type></council><name>Spezialkommission SR (01.074)</name></committee><function i:nil="true" /></committeeMembership><committeeMembership><id>7</id><updated>2010-12-26T13:07:50Z</updated><entryDate>2002-10-30T00:00:00Z</entryDate><leavingDate>2002-12-05T00:00:00Z</leavingDate><committee><id>28</id><updated>2010-12-26T13:06:13Z</updated><abbreviation>FinDel</abbreviation><code>KOM_28_</code><committeeNumber>28</committeeNumber><council><id>3</id><updated>2010-12-26T13:07:49Z</updated><abbreviation>V</abbreviation><code>RAT_3_</code><name>Vereinigte Bundesversammlung</name><type>B</type></council><name>Finanzdelegation</name></committee><function i:nil="true" /></committeeMembership><committeeMembership><id>8</id><updated>2010-12-26T13:07:50Z</updated><entryDate>2002-12-09T00:00:00Z</entryDate><leavingDate>2003-11-30T00:00:00Z</leavingDate><committee><id>28</id><updated>2010-12-26T13:06:13Z</updated><abbreviation>FinDel</abbreviation><code>KOM_28_</code><committeeNumber>28</committeeNumber><council><id>3</id><updated>2010-12-26T13:07:49Z</updated><abbreviation>V</abbreviation><code>RAT_3_</code><name>Vereinigte Bundesversammlung</name><type>B</type></council><name>Finanzdelegation</name></committee><function>Vizepräsident/in</function></committeeMembership><committeeMembership><id>13</id><updated>2010-12-26T13:07:50Z</updated><entryDate>2003-12-01T00:00:00Z</entryDate><leavingDate>2003-12-19T00:00:00Z</leavingDate><committee><id>547</id><updated>2012-03-28T15:54:08Z</updated><abbreviation>03.047-SR</abbreviation><code>KOM_547_</code><committeeNumber>547</committeeNumber><council><id>2</id><updated>2010-12-26T13:07:49Z</updated><abbreviation>SR</abbreviation><code>RAT_2_</code><name>Ständerat</name><type>S</type></council><name>Spezialkommission SR (03.047)</name></committee><function i:nil="true" /></committeeMembership><committeeMembership><id>10</id><updated>2010-12-26T13:07:50Z</updated><entryDate>2003-12-01T00:00:00Z</entryDate><leavingDate>2007-12-02T00:00:00Z</leavingDate><committee><id>596</id><updated>2012-03-28T16:09:02Z</updated><abbreviation>RehaKo</abbreviation><code>KOM_596_</code><committeeNumber>596</committeeNumber><council><id>3</id><updated>2010-12-26T13:07:49Z</updated><abbreviation>V</abbreviation><code>RAT_3_</code><name>Vereinigte Bundesversammlung</name><type>B</type></council><name>Rehabilitierungskommission V</name></committee><function i:nil="true" /></committeeMembership><committeeMembership><id>11</id><updated>2010-12-26T13:07:50Z</updated><entryDate>2003-12-01T00:00:00Z</entryDate><leavingDate>2007-12-02T00:00:00Z</leavingDate><committee><id>28</id><updated>2010-12-26T13:06:13Z</updated><abbreviation>FinDel</abbreviation><code>KOM_28_</code><committeeNumber>28</committeeNumber><council><id>3</id><updated>2010-12-26T13:07:49Z</updated><abbreviation>V</abbreviation><code>RAT_3_</code><name>Vereinigte Bundesversammlung</name><type>B</type></council><name>Finanzdelegation</name></committee><function i:nil="true" /></committeeMembership><committeeMembership><id>15</id><updated>2010-12-26T13:07:50Z</updated><entryDate>2004-02-25T00:00:00Z</entryDate><leavingDate>2004-06-16T00:00:00Z</leavingDate><committee><id>601</id><updated>2012-03-28T15:49:18Z</updated><abbreviation>04.012-SR</abbreviation><code>KOM_601_</code><committeeNumber>601</committeeNumber><council><id>2</id><updated>2010-12-26T13:07:49Z</updated><abbreviation>SR</abbreviation><code>RAT_2_</code><name>Ständerat</name><type>S</type></council><name>Kommission 04.012-SR</name></committee><function i:nil="true" /></committeeMembership><committeeMembership><id>16</id><updated>2010-12-26T13:07:50Z</updated><entryDate>2004-12-17T00:00:00Z</entryDate><leavingDate>2005-06-17T00:00:00Z</leavingDate><committee><id>632</id><updated>2012-03-28T16:02:32Z</updated><abbreviation>04.080-SR</abbreviation><code>KOM_632_</code><committeeNumber>632</committeeNumber><council><id>2</id><updated>2010-12-26T13:07:49Z</updated><abbreviation>SR</abbreviation><code>RAT_2_</code><name>Ständerat</name><type>S</type></council><name>Kommission 04.080-SR</name></committee><function i:nil="true" /></committeeMembership><committeeMembership><id>17</id><updated>2010-12-26T13:07:50Z</updated><entryDate>2005-09-29T00:00:00Z</entryDate><leavingDate>2006-10-06T00:00:00Z</leavingDate><committee><id>653</id><updated>2012-03-28T16:04:05Z</updated><abbreviation>05.070-SR</abbreviation><code>KOM_653_</code><committeeNumber>653</committeeNumber><council><id>2</id><updated>2010-12-26T13:07:49Z</updated><abbreviation>SR</abbreviation><code>RAT_2_</code><name>Ständerat</name><type>S</type></council><name>Kommission 05.070-SR</name></committee><function i:nil="true" /></committeeMembership><committeeMembership><id>19</id><updated>2010-12-26T13:07:50Z</updated><entryDate>2006-12-04T00:00:00Z</entryDate><leavingDate>2007-06-22T00:00:00Z</leavingDate><committee><id>676</id><updated>2012-03-28T16:08:01Z</updated><abbreviation>06.094-SR</abbreviation><code>KOM_676_</code><committeeNumber>676</committeeNumber><council><id>2</id><updated>2010-12-26T13:07:49Z</updated><abbreviation>SR</abbreviation><code>RAT_2_</code><name>Ständerat</name><type>S</type></council><name>Kommission 06.094-SR</name></committee><function i:nil="true" /></committeeMembership></committeeMemberships><concerns /><contact><emailPrivate>hans.lauri@bluewin.ch</emailPrivate><emailWork i:nil="true" /><faxPrivate i:nil="true" /><faxWork i:nil="true" /><homepagePrivate i:nil="true" /><homepageWork i:nil="true" /><phoneMobilePrivate i:nil="true" /><phoneMobileWork i:nil="true" /><phonePrivate i:nil="true" /><phoneWork i:nil="true" /></contact><councilMemberships><councilMembership><id>0</id><updated>2010-12-26T13:07:53Z</updated><entryDate>2001-06-05T00:00:00Z</entryDate><leavingDate>2003-11-30T00:00:00Z</leavingDate><canton>BE</canton><cantonName>Bern</cantonName><council><id>2</id><updated>2010-12-26T13:07:49Z</updated><abbreviation>SR</abbreviation><code>RAT_2_</code><name>Ständerat</name><type>S</type></council></councilMembership><councilMembership><id>1</id><updated>2010-12-26T13:07:53Z</updated><entryDate>2003-12-01T00:00:00Z</entryDate><leavingDate>2007-12-02T00:00:00Z</leavingDate><canton>BE</canton><cantonName>Bern</cantonName><council><id>2</id><updated>2010-12-26T13:07:49Z</updated><abbreviation>SR</abbreviation><code>RAT_2_</code><name>Ständerat</name><type>S</type></council></councilMembership></councilMemberships><displayLanguage>de</displayLanguage><domicile><canton i:nil="true" /><city i:nil="true" /><addressLine i:nil="true" /><zip>0</zip></domicile><gender>m</gender><homePlaces><homePlace><canton>AG</canton><city>Zofingen</city></homePlace></homePlaces><language>de</language><mandate>Regierungsrat des Kantons Bern (Finanzdirektor) von Juni 1994 bis  August 2001</mandate><maritalStatus>verheiratet</maritalStatus><militaryGrade>Oberst</militaryGrade><numberOfChildren>2</numberOfChildren><officialDenomination>Lauri</officialDenomination><postalAddress><canton>BE</canton><city>Münsingen</city><addressLine>Schwalbenweg 19</addressLine><zip>3110</zip></postalAddress><professions><profession>Direktor der Eidg. Zollverwaltung</profession><profession>Rechtsanwalt</profession><profession>Regierungsrat</profession><profession>Vizedirektor der Eidg. Finanzverwaltung</profession></professions><salutationLetter>Herr</salutationLetter><salutationTitle i:nil="true" /><title>Dr. iur.</title><workLanguage>de</workLanguage></councillor>